pennylane_orquestra/__init__.py
pennylane_orquestra/_version.py
pennylane_orquestra/cli_actions.py
pennylane_orquestra/forest_device.py
pennylane_orquestra/gen_workflow.py
pennylane_orquestra/ibmq_device.py
pennylane_orquestra/orquestra_device.py
pennylane_orquestra/qiskit_device.py
pennylane_orquestra/qulacs_device.py
pennylane_orquestra/utils.py
PennyLane_Orquestra-0.33.0.dist-info/LICENSE
PennyLane_Orquestra-0.33.0.dist-info/METADATA
PennyLane_Orquestra-0.33.0.dist-info/WHEEL
PennyLane_Orquestra-0.33.0.dist-info/entry_points.txt
PennyLane_Orquestra-0.33.0.dist-info/top_level.txt
PennyLane_Orquestra-0.33.0.dist-info/RECORD
