Metadata-Version: 2.1
Name: PennyLane-Orquestra
Version: 0.33.0
Summary: PennyLane plugin for Orquestra by Xanadu Inc.
Home-page: https://github.com/PennyLaneAI/pennylane-orquestra
Maintainer: Xanadu Inc.
Maintainer-email: software@xanadu.ai
License: UNKNOWN
Platform: UNKNOWN
Classifier: Programming Language :: Python :: 3
Classifier: Operating System :: OS Independent
Provides: pennylane_orquestra
License-File: LICENSE
Requires-Dist: pyyaml
Requires-Dist: pennylane <0.34,>=0.28
